netmagic/VERSION.py
netmagic/__init__.py
netmagic/common/__init__.py
netmagic/common/types.py
netmagic/common/utils.py
netmagic/common/classes/__init__.py
netmagic/common/classes/interface.py
netmagic/common/classes/pydantic.py
netmagic/common/classes/responses.py
netmagic/common/classes/status.py
netmagic/devices/__init__.py
netmagic/devices/network_device.py
netmagic/devices/router.py
netmagic/devices/switch.py
netmagic/devices/universal.py
netmagic/devices/vendors/__init__.py
netmagic/devices/vendors/brocade.py
netmagic/devices/vendors/cisco.py
netmagic/handlers/__init__.py
netmagic/handlers/connect.py
netmagic/handlers/excel_writer.py
netmagic/handlers/parse.py
netmagic/handlers/serial_connect.py
netmagic/sessions/__init__.py
netmagic/sessions/netconf.py
netmagic/sessions/restconf.py
netmagic/sessions/session.py
netmagic/sessions/terminal.py
tests/__init__.py
tests/devices/__init__.py
tests/devices/common.py
tests/devices/test_network_device.py
tests/devices/brocade/__init__.py
tests/devices/brocade/test_brocade_switch.py
tests/devices/cisco/__init__.py
tests/devices/cisco/test_cisco_switch.py
tests/test_sessions/__init__.py
tests/test_sessions/test_terminal.py
NetMagic-0.1.2.dist-info/METADATA
NetMagic-0.1.2.dist-info/WHEEL
NetMagic-0.1.2.dist-info/top_level.txt
NetMagic-0.1.2.dist-info/RECORD
